soft_phone/__init__.py
soft_phone/callbacks.py
soft_phone/exceptions.py
soft_phone/manage_pjsip.py
soft_phone/soft_phone.py
soft_phone-1.7.4.dist-info/DESCRIPTION.rst
soft_phone-1.7.4.dist-info/METADATA
soft_phone-1.7.4.dist-info/RECORD
soft_phone-1.7.4.dist-info/WHEEL
soft_phone-1.7.4.dist-info/metadata.json
soft_phone-1.7.4.dist-info/top_level.txt
